luckyun_logger/__init__.py
luckyun_logger/log_helper.py
tests/__init__.py
tests/test_logger.py
luckyun_logger-0.1.0.dist-info/METADATA
luckyun_logger-0.1.0.dist-info/WHEEL
luckyun_logger-0.1.0.dist-info/top_level.txt
luckyun_logger-0.1.0.dist-info/RECORD
