Metadata-Version: 2.1
Name: luckyun-logger
Version: 0.1.0
Summary: log helper
Author: lucksoft
Classifier: Development Status :: 3 - Alpha
Classifier: Intended Audience :: Developers
Classifier: License :: OSI Approved :: MIT License
Classifier: Programming Language :: Python :: 3
Classifier: Programming Language :: Python :: 3.6
Classifier: Programming Language :: Python :: 3.7
Classifier: Programming Language :: Python :: 3.8
Classifier: Programming Language :: Python :: 3.9
Requires-Dist: autopep8 (==2.0.2)
Requires-Dist: exceptiongroup (==1.1.1)
Requires-Dist: iniconfig (==2.0.0)
Requires-Dist: packaging (==23.1)
Requires-Dist: pluggy (==1.0.0)
Requires-Dist: pycodestyle (==2.10.0)
Requires-Dist: pytest (==7.3.1)
Requires-Dist: tomli (==2.0.1)
